cursorgen/__init__.py
cursorgen/__main__.py
cursorgen/parser/__init__.py
cursorgen/parser/ani.py
cursorgen/parser/base.py
cursorgen/parser/bmp.py
cursorgen/parser/cur.py
cursorgen/parser/xcursor.py
cursorgen/utils/__init__.py
cursorgen/utils/cursor.py
cursorgen/writer/__init__.py
cursorgen/writer/x11.py
cursorgen-0.1.3.dist-info/METADATA
cursorgen-0.1.3.dist-info/WHEEL
cursorgen-0.1.3.dist-info/entry_points.txt
cursorgen-0.1.3.dist-info/licenses/LICENSE.md
cursorgen-0.1.3.dist-info/RECORD
