Metadata-Version: 2.3
Name: cursorgen
Version: 0.1.3
Summary: cursorgen is a fork of win2xcur that aims to preserve the image quality of the cursor.
Project-URL: Homepage, https://github.com/ashuramaruzxc/cursorgen
Project-URL: Bug Reports, https://github.com/ashuramaruzxc/cursorgen/issues
Project-URL: Source, https://github.com/ashuramaruzxc/cursorgen
Author-email: ashuramaruzxc <ashuramaru@tenjin-dk.com>
Maintainer-email: ashuramaruzxc <ashuramaru@tenjin-dk.com>
License: GNU GENERAL PUBLIC LICENSE
License-File: LICENSE.md
Keywords: ani,cur,cursor,win32,windows,x11,xcursor
Classifier: Development Status :: 3 - Alpha
Classifier: Environment :: Win32 (MS Windows)
Classifier: Environment :: X11 Applications
Classifier: Intended Audience :: End Users/Desktop
Classifier: License :: OSI Approved :: GNU General Public License v3 or later (GPLv3+)
Classifier: Operating System :: Microsoft :: Windows
Classifier: Operating System :: POSIX :: Linux
Classifier: Programming Language :: Python
Classifier: Programming Language :: Python :: 3 :: Only
Classifier: Programming Language :: Python :: 3.8
Classifier: Programming Language :: Python :: 3.9
Classifier: Programming Language :: Python :: 3.10
Classifier: Programming Language :: Python :: 3.11
Classifier: Topic :: Desktop Environment
Requires-Python: >=3.7
Requires-Dist: numpy
Requires-Dist: pillow
